counter.v
module counter (
    input clk,
    input reset,   
    input [5:0] timer_value,
    output reg [5:0] counter_value

);
    reg [5:0] prev_timer_value;
    always @(negedge clk or posedge reset) begin
        if (reset) begin
            counter_value <= timer_value;
            prev_timer_value <= timer_value;
        end else if(timer_value != prev_timer_value) begin
                counter_value <= timer_value;
                prev_timer_value <= timer_value;
            end else if(counter_value > 0) begin
                counter_value <= counter_value - 1;
            end else begin
                counter_value <= 0; // Đảm bảo không âm
            end
        end

endmodule

counter_tb.v
`timescale 1ns/1ps
`include "counter.v"

module counter_tb;
    reg clk;
    reg reset;
    reg [5:0] timer_value;
    wire [5:0] counter_value;

    counter uut (
        .clk(clk),
        .reset(reset),
        .timer_value(timer_value),
        .counter_value(counter_value)
    );

    // Tạo xung clk 1Hz
    initial begin
        clk = 0;
        forever #500_000_000 clk = ~clk; // 0.5s mỗi cạnh => 1s chu kỳ
    end

    // Test chính
    initial begin
        $dumpfile("counter_tb.vcd");
        $dumpvars(0, counter_tb);

        // Reset hệ thống
        reset = 1;
        timer_value = 6'd18; // RED
        #1_000_000_000; // 1s

        reset = 0;

        // Chờ RED hết
        #18_000_000_000; // 18s

        // GREEN
        timer_value = 6'd15;
        #1_000_000_000; // 1s
        #15_000_000_000; // 15s

        // YELLOW
        timer_value = 6'd3;
        #1_000_000_000; // 1s
        #3_000_000_000; // 3s

        // Quay lại RED
        timer_value = 6'd18;
        #1_000_000_000; // 1s
        #18_000_000_000; // 18s

        $finish;
    end

endmodule

counter_tb.vcd
$date
	Fri Jun 13 09:18:25 2025
$end
$version
	Icarus Verilog
$end
$timescale
	1ps
$end
$scope module counter_tb $end
$var wire 6 ! counter_value [5:0] $end
$var reg 1 " clk $end
$var reg 1 # reset $end
$var reg 6 $ timer_value [5:0] $end
$scope module uut $end
$var wire 1 " clk $end
$var wire 1 # reset $end
$var wire 6 % timer_value [5:0] $end
$var reg 6 & counter_value [5:0] $end
$var reg 6 ' prev_timer_value [5:0] $end
$upscope $end
$upscope $end
$enddefinitions $end
$comment Show the parameter values. $end
$dumpall
$end
#0
$dumpvars
b10010 '
b10010 &
b10010 %
b10010 $
1#
0"
b10010 !
$end
#500000000000
1"
#1000000000000
b10001 !
b10001 &
0"
0#
#1500000000000
1"
#2000000000000
b10000 !
b10000 &
0"
#2500000000000
1"
#3000000000000
b1111 !
b1111 &
0"
#3500000000000
1"
#4000000000000
b1110 !
b1110 &
0"
#4500000000000
1"
#5000000000000
b1101 !
b1101 &
0"
#5500000000000
1"
#6000000000000
b1100 !
b1100 &
0"
#6500000000000
1"
#7000000000000
b1011 !
b1011 &
0"
#7500000000000
1"
#8000000000000
b1010 !
b1010 &
0"
#8500000000000
1"
#9000000000000
b1001 !
b1001 &
0"
#9500000000000
1"
#10000000000000
b1000 !
b1000 &
0"
#10500000000000
1"
#11000000000000
b111 !
b111 &
0"
#11500000000000
1"
#12000000000000
b110 !
b110 &
0"
#12500000000000
1"
#13000000000000
b101 !
b101 &
0"
#13500000000000
1"
#14000000000000
b100 !
b100 &
0"
#14500000000000
1"
#15000000000000
b11 !
b11 &
0"
#15500000000000
1"
#16000000000000
b10 !
b10 &
0"
#16500000000000
1"
#17000000000000
b1 !
b1 &
0"
#17500000000000
1"
#18000000000000
b0 !
b0 &
0"
#18500000000000
1"
#19000000000000
b1111 '
b1111 !
b1111 &
0"
b1111 $
b1111 %
#19500000000000
1"
#20000000000000
b1110 !
b1110 &
0"
#20500000000000
1"
#21000000000000
b1101 !
b1101 &
0"
#21500000000000
1"
#22000000000000
b1100 !
b1100 &
0"
#22500000000000
1"
#23000000000000
b1011 !
b1011 &
0"
#23500000000000
1"
#24000000000000
b1010 !
b1010 &
0"
#24500000000000
1"
#25000000000000
b1001 !
b1001 &
0"
#25500000000000
1"
#26000000000000
b1000 !
b1000 &
0"
#26500000000000
1"
#27000000000000
b111 !
b111 &
0"
#27500000000000
1"
#28000000000000
b110 !
b110 &
0"
#28500000000000
1"
#29000000000000
b101 !
b101 &
0"
#29500000000000
1"
#30000000000000
b100 !
b100 &
0"
#30500000000000
1"
#31000000000000
b11 !
b11 &
0"
#31500000000000
1"
#32000000000000
b10 !
b10 &
0"
#32500000000000
1"
#33000000000000
b1 !
b1 &
0"
#33500000000000
1"
#34000000000000
b0 !
b0 &
0"
#34500000000000
1"
#35000000000000
b11 '
b11 !
b11 &
0"
b11 $
b11 %
#35500000000000
1"
#36000000000000
b10 !
b10 &
0"
#36500000000000
1"
#37000000000000
b1 !
b1 &
0"
#37500000000000
1"
#38000000000000
b0 !
b0 &
0"
#38500000000000
1"
#39000000000000
b10010 '
b10010 !
b10010 &
0"
b10010 $
b10010 %
#39500000000000
1"
#40000000000000
b10001 !
b10001 &
0"
#40500000000000
1"
#41000000000000
b10000 !
b10000 &
0"
#41500000000000
1"
#42000000000000
b1111 !
b1111 &
0"
#42500000000000
1"
#43000000000000
b1110 !
b1110 &
0"
#43500000000000
1"
#44000000000000
b1101 !
b1101 &
0"
#44500000000000
1"
#45000000000000
b1100 !
b1100 &
0"
#45500000000000
1"
#46000000000000
b1011 !
b1011 &
0"
#46500000000000
1"
#47000000000000
b1010 !
b1010 &
0"
#47500000000000
1"
#48000000000000
b1001 !
b1001 &
0"
#48500000000000
1"
#49000000000000
b1000 !
b1000 &
0"
#49500000000000
1"
#50000000000000
b111 !
b111 &
0"
#50500000000000
1"
#51000000000000
b110 !
b110 &
0"
#51500000000000
1"
#52000000000000
b101 !
b101 &
0"
#52500000000000
1"
#53000000000000
b100 !
b100 &
0"
#53500000000000
1"
#54000000000000
b11 !
b11 &
0"
#54500000000000
1"
#55000000000000
b10 !
b10 &
0"
#55500000000000
1"
#56000000000000
b1 !
b1 &
0"
#56500000000000
1"
#57000000000000
b0 !
b0 &
0"
