light_counter.v
// Cho đèn sáng theo thứ tự: xanh, vàng, đỏ
// Đếm từ 14->0->2->17->0->14
module light_counter #(
    parameter pGREEN_INIT_VAL = 14,
    parameter pYELLOW_INIT_VAL = 2,
    parameter pRED_INIT_VAL = 17,
    parameter pCNT_WIDTH = 5, // log2(pRED_INIT_VAL+1)
    parameter pINIT_WIDTH = 3
)(
    input wire clk,
    input wire en,
    input wire rst_n,
    input wire [pINIT_WIDTH-1:0] init,
    output wire last,
    output wire [pCNT_WIDTH-1:0] cnt_out
);
    
    
    parameter pGREEN_IDX = 0;
    parameter pYELLOW_IDX = 1;
    parameter pRED_IDX = 2;
    
    
    reg [pCNT_WIDTH-1:0] count;
    
    
    always @(posedge clk or negedge rst_n) begin
        if (!rst_n) begin
            count <= pGREEN_INIT_VAL;
        end
        else if (init[pGREEN_IDX]) begin
            count <= pGREEN_INIT_VAL;
        end
        else if (init[pYELLOW_IDX]) begin
            count <= pYELLOW_INIT_VAL;
        end
        else if (init[pRED_IDX]) begin
            count <= pRED_INIT_VAL;
        end
        else if (en) begin
            count <= count - 1;
        end
    end
    
   
    assign last = (count == 0) ? 1'b1 : 1'b0;
    assign cnt_out = count;

endmodule

light_counter_tb.v
`timescale 1ns/1ps
`include "light_counter.v"
module light_counter_tb;

    // Parameters
    parameter pGREEN_INIT_VAL  = 14;
    parameter pYELLOW_INIT_VAL = 2;
    parameter pRED_INIT_VAL    = 17;
    parameter pCNT_WIDTH       = 5; // log2(pRED_INIT_VAL+1)
    parameter pINIT_WIDTH      = 3;
    parameter CLK_PERIOD       = 10;

    // Signals
    reg clk;
    reg rst_n;
    reg en;
    reg [pINIT_WIDTH-1:0] init;
    wire last;
    wire [pCNT_WIDTH-1:0] cnt_out;

    // Instantiate DUT
    light_counter #(
        .pGREEN_INIT_VAL(pGREEN_INIT_VAL),
        .pYELLOW_INIT_VAL(pYELLOW_INIT_VAL),
        .pRED_INIT_VAL(pRED_INIT_VAL),
        .pCNT_WIDTH(pCNT_WIDTH),
        .pINIT_WIDTH(pINIT_WIDTH)
    ) uut (
        .clk(clk),
        .en(en),
        .rst_n(rst_n),
        .init(init),
        .last(last),
        .cnt_out(cnt_out)
    );

    // Clock generator
    always #(CLK_PERIOD/2) clk = ~clk;

    // VCD
    initial begin
        $dumpfile("light_counter_tb.vcd");
        $dumpvars(0, light_counter_tb);
    end

    // Test procedure
    initial begin
        // Initial values
        clk = 0;
        rst_n = 0;
        en = 0;
        init = 3'b000;

        // Reset
        #20;
        rst_n = 1;

        // Start with GREEN
        #10;
        init = 3'b001; // GREEN
        #10;
        init = 3'b000;
        en = 1;

        // Wait until GREEN expires
        wait (last);
        #10;
        en = 0;

        // Set YELLOW
        init = 3'b010;
        #10;
        init = 3'b000;
        en = 1;

        // Wait until YELLOW expires
        wait (last);
        #10;
        en = 0;

        // Set RED
        init = 3'b100;
        #10;
        init = 3'b000;
        en = 1;

        // Wait until RED expires
        wait (last);
        #10;
        en = 0;

        // Back to GREEN
        init = 3'b001;
        #10;
        init = 3'b000;
        en = 1;

        // Run for a bit then finish
        #(20 * CLK_PERIOD);
        $finish;
    end

endmodule

light_counter_tb.vcd
$date
	Sun Jun 15 16:14:25 2025
$end
$version
	Icarus Verilog
$end
$timescale
	1ps
$end
$scope module light_counter_tb $end
$var wire 1 ! last $end
$var wire 5 " cnt_out [4:0] $end
$var parameter 32 # CLK_PERIOD $end
$var parameter 32 $ pCNT_WIDTH $end
$var parameter 32 % pGREEN_INIT_VAL $end
$var parameter 32 & pINIT_WIDTH $end
$var parameter 32 ' pRED_INIT_VAL $end
$var parameter 32 ( pYELLOW_INIT_VAL $end
$var reg 1 ) clk $end
$var reg 1 * en $end
$var reg 3 + init [2:0] $end
$var reg 1 , rst_n $end
$scope module uut $end
$var wire 1 ) clk $end
$var wire 5 - cnt_out [4:0] $end
$var wire 1 * en $end
$var wire 3 . init [2:0] $end
$var wire 1 , rst_n $end
$var wire 1 ! last $end
$var parameter 32 / pCNT_WIDTH $end
$var parameter 32 0 pGREEN_IDX $end
$var parameter 32 1 pGREEN_INIT_VAL $end
$var parameter 32 2 pINIT_WIDTH $end
$var parameter 32 3 pRED_IDX $end
$var parameter 32 4 pRED_INIT_VAL $end
$var parameter 32 5 pYELLOW_IDX $end
$var parameter 32 6 pYELLOW_INIT_VAL $end
$var reg 5 7 count [4:0] $end
$upscope $end
$upscope $end
$enddefinitions $end
$comment Show the parameter values. $end
$dumpall
b10 6
b1 5
b10001 4
b10 3
b11 2
b1110 1
b0 0
b101 /
b10 (
b10001 '
b11 &
b1110 %
b101 $
b1010 #
$end
#0
$dumpvars
b1110 7
b0 .
b1110 -
0,
b0 +
0*
0)
b1110 "
0!
$end
#5000
1)
#10000
0)
#15000
1)
#20000
0)
1,
#25000
1)
#30000
0)
b1 +
b1 .
#35000
1)
#40000
0)
1*
b0 +
b0 .
#45000
b1101 "
b1101 -
b1101 7
1)
#50000
0)
#55000
b1100 "
b1100 -
b1100 7
1)
#60000
0)
#65000
b1011 "
b1011 -
b1011 7
1)
#70000
0)
#75000
b1010 "
b1010 -
b1010 7
1)
#80000
0)
#85000
b1001 "
b1001 -
b1001 7
1)
#90000
0)
#95000
b1000 "
b1000 -
b1000 7
1)
#100000
0)
#105000
b111 "
b111 -
b111 7
1)
#110000
0)
#115000
b110 "
b110 -
b110 7
1)
#120000
0)
#125000
b101 "
b101 -
b101 7
1)
#130000
0)
#135000
b100 "
b100 -
b100 7
1)
#140000
0)
#145000
b11 "
b11 -
b11 7
1)
#150000
0)
#155000
b10 "
b10 -
b10 7
1)
#160000
0)
#165000
b1 "
b1 -
b1 7
1)
#170000
0)
#175000
1!
b0 "
b0 -
b0 7
1)
#180000
0)
#185000
0!
b10 "
b10 -
b10 7
1)
b10 +
b10 .
0*
#190000
0)
#195000
b1 "
b1 -
b1 7
1)
1*
b0 +
b0 .
#200000
0)
#205000
1!
b0 "
b0 -
b0 7
1)
#210000
0)
#215000
0!
b10001 "
b10001 -
b10001 7
1)
b100 +
b100 .
0*
#220000
0)
#225000
b10000 "
b10000 -
b10000 7
1)
1*
b0 +
b0 .
#230000
0)
#235000
b1111 "
b1111 -
b1111 7
1)
#240000
0)
#245000
b1110 "
b1110 -
b1110 7
1)
#250000
0)
#255000
b1101 "
b1101 -
b1101 7
1)
#260000
0)
#265000
b1100 "
b1100 -
b1100 7
1)
#270000
0)
#275000
b1011 "
b1011 -
b1011 7
1)
#280000
0)
#285000
b1010 "
b1010 -
b1010 7
1)
#290000
0)
#295000
b1001 "
b1001 -
b1001 7
1)
#300000
0)
#305000
b1000 "
b1000 -
b1000 7
1)
#310000
0)
#315000
b111 "
b111 -
b111 7
1)
#320000
0)
#325000
b110 "
b110 -
b110 7
1)
#330000
0)
#335000
b101 "
b101 -
b101 7
1)
#340000
0)
#345000
b100 "
b100 -
b100 7
1)
#350000
0)
#355000
b11 "
b11 -
b11 7
1)
#360000
0)
#365000
b10 "
b10 -
b10 7
1)
#370000
0)
#375000
b1 "
b1 -
b1 7
1)
#380000
0)
#385000
1!
b0 "
b0 -
b0 7
1)
#390000
0)
#395000
0!
b1110 "
b1110 -
b1110 7
1)
b1 +
b1 .
0*
#400000
0)
#405000
b1101 "
b1101 -
b1101 7
1)
1*
b0 +
b0 .
#410000
0)
#415000
b1100 "
b1100 -
b1100 7
1)
#420000
0)
#425000
b1011 "
b1011 -
b1011 7
1)
#430000
0)
#435000
b1010 "
b1010 -
b1010 7
1)
#440000
0)
#445000
b1001 "
b1001 -
b1001 7
1)
#450000
0)
#455000
b1000 "
b1000 -
b1000 7
1)
#460000
0)
#465000
b111 "
b111 -
b111 7
1)
#470000
0)
#475000
b110 "
b110 -
b110 7
1)
#480000
0)
#485000
b101 "
b101 -
b101 7
1)
#490000
0)
#495000
b100 "
b100 -
b100 7
1)
#500000
0)
#505000
b11 "
b11 -
b11 7
1)
#510000
0)
#515000
b10 "
b10 -
b10 7
1)
#520000
0)
#525000
b1 "
b1 -
b1 7
1)
#530000
0)
#535000
1!
b0 "
b0 -
b0 7
1)
#540000
0)
#545000
0!
b11111 "
b11111 -
b11111 7
1)
#550000
0)
#555000
b11110 "
b11110 -
b11110 7
1)
#560000
0)
#565000
b11101 "
b11101 -
b11101 7
1)
#570000
0)
#575000
b11100 "
b11100 -
b11100 7
1)
#580000
0)
#585000
b11011 "
b11011 -
b11011 7
1)
#590000
0)
#595000
b11010 "
b11010 -
b11010 7
1)
#600000
0)
#605000
b11001 "
b11001 -
b11001 7
1)
