segment_display.v
module segment_display (
    input      [5:0] count_value,
    output     [6:0] seg_a,
    output     [6:0] seg_b
);

    wire [3:0] digit_a; // hàng chục
    wire [3:0] digit_b; // hàng đơn vị

    assign digit_a = count_value / 10;
    assign digit_b = count_value % 10;

    display dis_a (
        .value(digit_a),
        .seg(seg_a)
    );

    display dis_b (
        .value(digit_b),
        .seg(seg_b)
    );

endmodule

module display (
    input  [3:0] value,
    output reg [6:0] seg
);

    always @(*) begin
        case (value)
            4'd0: seg = 7'b1111110;
            4'd1: seg = 7'b0110000;
            4'd2: seg = 7'b1101101;
            4'd3: seg = 7'b1111001;
            4'd4: seg = 7'b0110011;
            4'd5: seg = 7'b1011011;
            4'd6: seg = 7'b1011111;
            4'd7: seg = 7'b1110000;
            4'd8: seg = 7'b1111111;
            4'd9: seg = 7'b1111011;
            default: seg = 7'b0000000;
        endcase
    end

endmodule

segmet_display_tb.v
`timescale 1ns/1ps
`include "segment_display.v"

module segment_display_tb;

    reg [5:0] count_value;
    wire [6:0] seg_a;
    wire [6:0] seg_b;

    segment_display uut (
        .count_value(count_value),
        .seg_a(seg_a),
        .seg_b(seg_b)
    );

    initial begin
        $dumpfile("segment_display_tb.vcd");
        $dumpvars(0, segment_display_tb);
        // Test case 1: count_value = 0
        count_value = 6'd0;
        #10;
        
        // Test case 2: count_value = 5
        count_value = 6'd18;
        #10;

        // Test case 3: count_value = 10
        count_value = 6'd15;
        #10;

        // Test case 4: count_value = 15
        count_value = 6'd3;
        #10;

        // Test case 5: count_value = 20
        count_value = 6'd20;
        #10;

        // Test case 6: count_value = 35
        count_value = 6'd35;
        #10;

        // Test case 7: count_value = 50
        count_value = 6'd50;
        #10;

        // Test case 8: count_value = 63 (maximum for a 6-bit value)
        count_value = 6'd63;
        #10;

        $finish; // End simulation
    end

endmodule

segment_display_tb.vcd
$date
	Fri Jun 13 09:37:26 2025
$end
$version
	Icarus Verilog
$end
$timescale
	1ps
$end
$scope module segment_display_tb $end
$var wire 7 ! seg_b [6:0] $end
$var wire 7 " seg_a [6:0] $end
$var reg 6 # count_value [5:0] $end
$scope module uut $end
$var wire 6 $ count_value [5:0] $end
$var wire 7 % seg_b [6:0] $end
$var wire 7 & seg_a [6:0] $end
$var wire 4 ' digit_b [3:0] $end
$var wire 4 ( digit_a [3:0] $end
$scope module dis_a $end
$var wire 4 ) value [3:0] $end
$var reg 7 * seg [6:0] $end
$upscope $end
$scope module dis_b $end
$var wire 4 + value [3:0] $end
$var reg 7 , seg [6:0] $end
$upscope $end
$upscope $end
$upscope $end
$enddefinitions $end
$comment Show the parameter values. $end
$dumpall
$end
#0
$dumpvars
b1111110 ,
b0 +
b1111110 *
b0 )
b0 (
b0 '
b1111110 &
b1111110 %
b0 $
b0 #
b1111110 "
b1111110 !
$end
#10000
b110000 "
b110000 &
b110000 *
b1111111 !
b1111111 %
b1111111 ,
b1 (
b1 )
b1000 '
b1000 +
b10010 #
b10010 $
#20000
b1011011 !
b1011011 %
b1011011 ,
b101 '
b101 +
b1111 #
b1111 $
#30000
b1111110 "
b1111110 &
b1111110 *
b1111001 !
b1111001 %
b1111001 ,
b0 (
b0 )
b11 '
b11 +
b11 #
b11 $
#40000
b1101101 "
b1101101 &
b1101101 *
b1111110 !
b1111110 %
b1111110 ,
b10 (
b10 )
b0 '
b0 +
b10100 #
b10100 $
#50000
b1111001 "
b1111001 &
b1111001 *
b1011011 !
b1011011 %
b1011011 ,
b11 (
b11 )
b101 '
b101 +
b100011 #
b100011 $
#60000
b1011011 "
b1011011 &
b1011011 *
b1111110 !
b1111110 %
b1111110 ,
b101 (
b101 )
b0 '
b0 +
b110010 #
b110010 $
#70000
b1011111 "
b1011111 &
b1011111 *
b1111001 !
b1111001 %
b1111001 ,
b110 (
b110 )
b11 '
b11 +
b111111 #
b111111 $
