traffic_fsm.v
// điều khiển trạng thái
module traffic_fsm #(
    parameter LIGHT_STATE_WIDTH = 3
)(
    input wire clk,
    input wire en,
    input wire rst_n,
    input wire light_cnt_last,
    input wire second_cnt_pre_last,
    output wire [LIGHT_STATE_WIDTH-1:0] light,
    output wire [LIGHT_STATE_WIDTH-1:0] light_cnt_init
);
    
//. Định nghĩa các tham số đèn
    parameter pGREEN_IDX = 0;
    parameter pYELLOW_IDX = 1;
    parameter pRED_IDX = 2;
    
    // Trạng thái của đèn
    parameter [1:0] IDLE = 2'b00;
    parameter [1:0] GREEN = 2'b01;
    parameter [1:0] YELLOW = 2'b10;
    parameter [1:0] RED = 2'b11;
    
   
    reg [1:0] light_current_state, light_next_state;
    reg [LIGHT_STATE_WIDTH-1:0] signal_light;
    reg [LIGHT_STATE_WIDTH-1:0] signal_light_cnt_init;
    
    
    wire last_cnt;
    assign last_cnt = light_cnt_last & second_cnt_pre_last;
    
    // Trạng thái khi reset, en, và kích hoạt
    always @(posedge clk or negedge rst_n) begin
        if (!rst_n) begin
            light_current_state <= IDLE;
        end
        else if (en) begin
            light_current_state <= light_next_state;
        end
        else begin
            light_current_state <= IDLE;
        end
    end
    
    
    always @(*) begin
        light_next_state = IDLE;
        signal_light = 3'b000;
        signal_light_cnt_init = 3'b000;
        
        case (light_current_state)
            // Trạng thái IDLE: đèn tắt
            IDLE: begin
                if (en) begin
                    light_next_state = GREEN;
                    signal_light[pGREEN_IDX] = 1'b1;
                end
                else begin
                    light_next_state = IDLE;
                    signal_light = 3'b000;
                    signal_light_cnt_init = 3'b000;
                end
            end
            
            GREEN: begin
                if (last_cnt) begin
                    light_next_state = YELLOW;
                    signal_light[pYELLOW_IDX] = 1'b1;
                    signal_light_cnt_init[pYELLOW_IDX] = 1'b1;
                end
                else begin
                    light_next_state = GREEN;
                    signal_light[pGREEN_IDX] = 1'b1;
                end
            end
            
            YELLOW: begin
                if (last_cnt) begin
                    light_next_state = RED;
                    signal_light[pRED_IDX] = 1'b1;
                    signal_light_cnt_init[pRED_IDX] = 1'b1;
                end
                else begin
                    light_next_state = YELLOW;
                    signal_light[pYELLOW_IDX] = 1'b1;
                end
            end
            
            RED: begin
                if (last_cnt) begin
                    light_next_state = GREEN;
                    signal_light[pGREEN_IDX] = 1'b1;
                    signal_light_cnt_init[pGREEN_IDX] = 1'b1;
                end
                else begin
                    light_next_state = RED;
                    signal_light[pRED_IDX] = 1'b1;
                end
            end
        endcase
    end
    
    // Output assignments
    assign light = signal_light;
    assign light_cnt_init = signal_light_cnt_init;

endmodule

traffic_fsm_tb.v
`timescale 1ns/1ps
`include "traffic_fsm.v"
module traffic_fsm_tb;

    // Parameters
    parameter LIGHT_STATE_WIDTH = 3;
    parameter CLK_PERIOD = 10;

    // Inputs
    reg clk;
    reg rst_n;
    reg en;
    reg light_cnt_last;
    reg second_cnt_pre_last;

    // Outputs
    wire [LIGHT_STATE_WIDTH-1:0] light;
    wire [LIGHT_STATE_WIDTH-1:0] light_cnt_init;

    // Instantiate the DUT
    traffic_fsm #(
        .LIGHT_STATE_WIDTH(LIGHT_STATE_WIDTH)
    ) uut (
        .clk(clk),
        .en(en),
        .rst_n(rst_n),
        .light_cnt_last(light_cnt_last),
        .second_cnt_pre_last(second_cnt_pre_last),
        .light(light),
        .light_cnt_init(light_cnt_init)
    );

    // Clock generator
    always #(CLK_PERIOD / 2) clk = ~clk;

    // VCD file
    initial begin
        $dumpfile("traffic_fsm_tb.vcd");
        $dumpvars(0, traffic_fsm_tb);
    end

    // Test procedure
    initial begin
        // Initial values
        clk = 0;
        rst_n = 0;
        en = 0;
        light_cnt_last = 0;
        second_cnt_pre_last = 0;

        // Apply reset
        #20;
        rst_n = 1;

        // Enable FSM
        en = 1;

        // Wait in GREEN state
        #20;

        // Trigger transition GREEN -> YELLOW
        light_cnt_last = 1;
        second_cnt_pre_last = 1;
        #10;
        light_cnt_last = 0;
        second_cnt_pre_last = 0;

        // Wait in YELLOW state
        #30;

        // Trigger transition YELLOW -> RED
        light_cnt_last = 1;
        second_cnt_pre_last = 1;
        #10;
        light_cnt_last = 0;
        second_cnt_pre_last = 0;

        // Wait in RED state
        #30;

        // Trigger transition RED -> GREEN
        light_cnt_last = 1;
        second_cnt_pre_last = 1;
        #10;
        light_cnt_last = 0;
        second_cnt_pre_last = 0;

        // Wait in GREEN again
        #30;

        // Disable FSM
        en = 0;
        #20;

        // Apply reset
        rst_n = 0;
        #10;
        rst_n = 1;

        // Finish simulation
        #20;
        $finish;
    end

endmodule

traffic_fsm_tb.vcd
$date
	Sun Jun 15 16:17:30 2025
$end
$version
	Icarus Verilog
$end
$timescale
	1ps
$end
$scope module traffic_fsm_tb $end
$var wire 3 ! light_cnt_init [2:0] $end
$var wire 3 " light [2:0] $end
$var parameter 32 # CLK_PERIOD $end
$var parameter 32 $ LIGHT_STATE_WIDTH $end
$var reg 1 % clk $end
$var reg 1 & en $end
$var reg 1 ' light_cnt_last $end
$var reg 1 ( rst_n $end
$var reg 1 ) second_cnt_pre_last $end
$scope module uut $end
$var wire 1 % clk $end
$var wire 1 & en $end
$var wire 1 * last_cnt $end
$var wire 3 + light [2:0] $end
$var wire 3 , light_cnt_init [2:0] $end
$var wire 1 ' light_cnt_last $end
$var wire 1 ( rst_n $end
$var wire 1 ) second_cnt_pre_last $end
$var parameter 2 - GREEN $end
$var parameter 2 . IDLE $end
$var parameter 32 / LIGHT_STATE_WIDTH $end
$var parameter 2 0 RED $end
$var parameter 2 1 YELLOW $end
$var parameter 32 2 pGREEN_IDX $end
$var parameter 32 3 pRED_IDX $end
$var parameter 32 4 pYELLOW_IDX $end
$var reg 2 5 light_current_state [1:0] $end
$var reg 2 6 light_next_state [1:0] $end
$var reg 3 7 signal_light [2:0] $end
$var reg 3 8 signal_light_cnt_init [2:0] $end
$upscope $end
$upscope $end
$enddefinitions $end
$comment Show the parameter values. $end
$dumpall
b1 4
b10 3
b0 2
b10 1
b11 0
b11 /
b0 .
b1 -
b11 $
b1010 #
$end
#0
$dumpvars
b0 8
b0 7
b0 6
b0 5
b0 ,
b0 +
0*
0)
0(
0'
0&
0%
b0 "
b0 !
$end
#5000
1%
#10000
0%
#15000
1%
#20000
b1 "
b1 +
b1 7
b1 6
0%
1&
1(
#25000
b1 "
b1 +
b1 7
b1 6
b1 5
1%
#30000
0%
#35000
1%
#40000
b10 !
b10 ,
b10 8
b10 "
b10 +
b10 7
b10 6
1*
0%
1)
1'
#45000
b100 !
b100 ,
b100 8
b100 "
b100 +
b100 7
b11 6
b10 5
1%
#50000
b0 !
b0 ,
b0 8
b10 "
b10 +
b10 7
b10 6
0*
0%
0)
0'
#55000
1%
#60000
0%
#65000
1%
#70000
0%
#75000
1%
#80000
b100 !
b100 ,
b100 8
b100 "
b100 +
b100 7
b11 6
1*
0%
1)
1'
#85000
b1 !
b1 ,
b1 8
b1 "
b1 +
b1 7
b1 6
b11 5
1%
#90000
b0 !
b0 ,
b0 8
b100 "
b100 +
b100 7
b11 6
0*
0%
0)
0'
#95000
1%
#100000
0%
#105000
1%
#110000
0%
#115000
1%
#120000
b1 !
b1 ,
b1 8
b1 "
b1 +
b1 7
b1 6
1*
0%
1)
1'
#125000
b10 !
b10 ,
b10 8
b10 "
b10 +
b10 7
b10 6
b1 5
1%
#130000
b0 !
b0 ,
b0 8
b1 "
b1 +
b1 7
b1 6
0*
0%
0)
0'
#135000
1%
#140000
0%
#145000
1%
#150000
0%
#155000
1%
#160000
b1 "
b1 +
b1 7
b1 6
0%
0&
#165000
b0 "
b0 +
b0 7
b0 6
b0 5
1%
#170000
0%
#175000
1%
#180000
0%
0(
#185000
1%
#190000
0%
1(
