traffic_fsm.v
module traffic_fsm#(
    parameter LIGHT_STATE_WIDTH = 3
)(
    input wire clk,
    input wire rst_n,
    input wire en,
    input wire second_cnt_pre_last,
    input wire light_cnt_last,
    output wire [LIGHT_STATE_WIDTH-1:0] light,
    output wire [LIGHT_STATE_WIDTH-1:0] light_cnt_init
);

    // Light indices
    parameter pGREEN_LIGHT  = 0;
    parameter pYELLOW_LIGHT = 1;
    parameter pRED_LIGHT    = 2;

    // FSM states
    parameter pIDLE = 2'b00;
    parameter pGREEN = 2'b01;
    parameter pYELLOW = 2'b10;
    parameter pRED = 2'b11;

    // State registers
    reg [1:0] light_current_state, light_next_state;

    // Output registers
    reg [LIGHT_STATE_WIDTH-1:0] signal_current_light;
    reg [LIGHT_STATE_WIDTH-1:0] signal_current_init;
    reg [LIGHT_STATE_WIDTH-1:0] signal_next_light;
    reg [LIGHT_STATE_WIDTH-1:0] signal_next_init;

    // Last count signal
    wire last_cnt;
    assign last_cnt = light_cnt_last & second_cnt_pre_last;

    assign light = signal_current_light;
    assign light_cnt_init = signal_current_init;

    // State transition
    always @(posedge clk or negedge rst_n) begin
        if (!rst_n) begin
            light_current_state <= pIDLE;
            signal_current_light <= 0;
            signal_current_init <= 0;
        end else if (en) begin
            light_current_state <= light_next_state;
            signal_current_light <= signal_next_light;
            signal_current_init <= signal_next_init;
        end else begin
            light_current_state <= pIDLE;
            signal_current_light <= 0;
            signal_current_init <= 0;
        end
    end

    // Combinational logic
    always @(*) begin
        light_next_state = pIDLE;
        signal_next_light = 0;
        signal_next_init = 0;

        case (light_current_state)
            pIDLE: begin
                if (en) begin
                    light_next_state = pGREEN;
                    signal_next_light[pGREEN_LIGHT] = 1'b1;
                    signal_next_init[pGREEN_LIGHT] = 1'b1;
                end
            end

            pGREEN: begin
                if (last_cnt) begin
                    light_next_state = pYELLOW;
                    signal_next_light[pYELLOW_LIGHT] = 1'b1;
                    signal_next_init[pYELLOW_LIGHT] = 1'b1;
                end else begin
                    light_next_state = pGREEN;
                    signal_next_light[pGREEN_LIGHT] = 1'b1;
                    signal_next_init[pGREEN_LIGHT] = 1'b1;
                end
            end

            pYELLOW: begin
                if (last_cnt) begin
                    light_next_state = pRED;
                    signal_next_light[pRED_LIGHT] = 1'b1;
                    signal_next_init[pRED_LIGHT] = 1'b1;
                end else begin
                    light_next_state = pYELLOW;
                    signal_next_light[pYELLOW_LIGHT] = 1'b1;
                    signal_next_init[pYELLOW_LIGHT] = 1'b1;
                end
            end

            pRED: begin
                if (last_cnt) begin
                    light_next_state = pGREEN;
                    signal_next_light[pGREEN_LIGHT] = 1'b1;
                    signal_next_init[pGREEN_LIGHT] = 1'b1;
                end else begin
                    light_next_state = pRED;
                    signal_next_light[pRED_LIGHT] = 1'b1;
                    signal_next_init[pRED_LIGHT] = 1'b1;
                end
            end
        endcase
    end

endmodule

traffic_fsm_tb.v
`timescale 1ns/1ps
`include "traffic_fsm.v"

module traffic_fsm_tb;

  parameter LIGHT_STATE_WIDTH = 3;

  // Testbench signals
  reg clk;
  reg en;
  reg rst_n;
  reg light_cnt_last;
  reg second_cnt_pre_last;

  wire [LIGHT_STATE_WIDTH-1:0] light;
  wire [LIGHT_STATE_WIDTH-1:0] light_cnt_init;

  // Instantiate the Unit Under Test (UUT)
  traffic_fsm #(.LIGHT_STATE_WIDTH(LIGHT_STATE_WIDTH)) uut (
    .clk(clk),
    .en(en),
    .rst_n(rst_n),
    .light_cnt_last(light_cnt_last),
    .second_cnt_pre_last(second_cnt_pre_last),
    .light(light),
    .light_cnt_init(light_cnt_init)
  );

  // Clock generation: 10ns period
  always #5 clk = ~clk;

  // Simulation control
  initial begin
    // VCD for waveform
    $dumpfile("traffic_fsm_tb.vcd");
    $dumpvars(0, traffic_fsm_tb);

    // Initialize
    clk = 0;
    rst_n = 0;
    en = 0;
    light_cnt_last = 0;
    second_cnt_pre_last = 0;

    // Apply reset
    #10 rst_n = 1;

    // Enable FSM one time after reset
    #10 en = 1;

    // Keep FSM running with en=1 forever (no toggling)
    // === GREEN phase (IDLE -> GREEN)
    #30;
    toggle_last_cnt(); // trigger to YELLOW

    // === YELLOW phase
    #40;
    toggle_last_cnt(); // trigger to RED

    // === RED phase
    #50;
    toggle_last_cnt(); // trigger to GREEN again

    // === GREEN again
    #40;
    toggle_last_cnt(); // loop continues...

    // Wait and finish
    #100;
    $finish;
  end

  // Task: toggle both last flags high for one cycle
  task toggle_last_cnt;
    begin
      light_cnt_last = 1;
      second_cnt_pre_last = 1;
      #10;
      light_cnt_last = 0;
      second_cnt_pre_last = 0;
    end
  endtask

  // Optional: Human-readable light display
  always @(posedge clk) begin
    case (light)
      3'b001: $display("%t: 🟢 GREEN Light ON", $time);
      3'b010: $display("%t: 🟡 YELLOW Light ON", $time);
      3'b100: $display("%t: 🔴 RED Light ON", $time);
      default: $display("%t: --- No Light Active ---", $time);
    endcase
  end

endmodule

traffic_fsm_tb.vcd
$date
	Sat Jun 14 11:04:02 2025
$end
$version
	Icarus Verilog
$end
$timescale
	1ps
$end
$scope module traffic_fsm_tb $end
$var wire 3 ! light_cnt_init [2:0] $end
$var wire 3 " light [2:0] $end
$var parameter 32 # LIGHT_STATE_WIDTH $end
$var reg 1 $ clk $end
$var reg 1 % en $end
$var reg 1 & light_cnt_last $end
$var reg 1 ' rst_n $end
$var reg 1 ( second_cnt_pre_last $end
$scope module uut $end
$var wire 1 $ clk $end
$var wire 1 % en $end
$var wire 1 ) last_cnt $end
$var wire 3 * light [2:0] $end
$var wire 3 + light_cnt_init [2:0] $end
$var wire 1 & light_cnt_last $end
$var wire 1 ' rst_n $end
$var wire 1 ( second_cnt_pre_last $end
$var parameter 32 , LIGHT_STATE_WIDTH $end
$var parameter 2 - pGREEN $end
$var parameter 32 . pGREEN_LIGHT $end
$var parameter 2 / pIDLE $end
$var parameter 2 0 pRED $end
$var parameter 32 1 pRED_LIGHT $end
$var parameter 2 2 pYELLOW $end
$var parameter 32 3 pYELLOW_LIGHT $end
$var reg 2 4 light_current_state [1:0] $end
$var reg 2 5 light_next_state [1:0] $end
$var reg 3 6 signal_current_init [2:0] $end
$var reg 3 7 signal_current_light [2:0] $end
$var reg 3 8 signal_next_init [2:0] $end
$var reg 3 9 signal_next_light [2:0] $end
$upscope $end
$scope task toggle_last_cnt $end
$upscope $end
$upscope $end
$enddefinitions $end
$comment Show the parameter values. $end
$dumpall
b1 3
b10 2
b10 1
b11 0
b0 /
b0 .
b1 -
b11 ,
b11 #
$end
#0
$dumpvars
b0 9
b0 8
b0 7
b0 6
b0 5
b0 4
b0 +
b0 *
0)
0(
0'
0&
0%
0$
b0 "
b0 !
$end
#5000
1$
#10000
0$
1'
#15000
1$
#20000
b1 8
b1 9
b1 5
0$
1%
#25000
b1 8
b1 9
b1 5
b1 !
b1 +
b1 6
b1 "
b1 *
b1 7
b1 4
1$
#30000
0$
#35000
1$
#40000
0$
#45000
1$
#50000
b10 8
b10 9
b10 5
1)
0$
1(
1&
#55000
b100 8
b100 9
b11 5
b10 !
b10 +
b10 6
b10 "
b10 *
b10 7
b10 4
1$
#60000
b10 8
b10 9
b10 5
0)
0$
0(
0&
#65000
1$
#70000
0$
#75000
1$
#80000
0$
#85000
1$
#90000
0$
#95000
1$
#100000
b100 8
b100 9
b11 5
1)
0$
1(
1&
#105000
b1 8
b1 9
b1 5
b100 !
b100 +
b100 6
b100 "
b100 *
b100 7
b11 4
1$
#110000
b100 8
b100 9
b11 5
0)
0$
0(
0&
#115000
1$
#120000
0$
#125000
1$
#130000
0$
#135000
1$
#140000
0$
#145000
1$
#150000
0$
#155000
1$
#160000
b1 8
b1 9
b1 5
1)
0$
1(
1&
#165000
b10 8
b10 9
b10 5
b1 !
b1 +
b1 6
b1 "
b1 *
b1 7
b1 4
1$
#170000
b1 8
b1 9
b1 5
0)
0$
0(
0&
#175000
1$
#180000
0$
#185000
1$
#190000
0$
#195000
1$
#200000
0$
#205000
1$
#210000
b10 8
b10 9
b10 5
1)
0$
1(
1&
#215000
b100 8
b100 9
b11 5
b10 !
b10 +
b10 6
b10 "
b10 *
b10 7
b10 4
1$
#220000
b10 8
b10 9
b10 5
0)
0$
0(
0&
