traffic_fsm_single.v
module traffic_fsm_single(
    input clk,
    input rst_n,
    output reg [1:0] led // 00: Red, 01: Green, 10: Yellow
);

    reg [1:0] state;
    reg [4:0] counter; // để đếm giây (1Hz)

    // Định nghĩa trạng thái
    localparam S_RED    = 2'b00,
               S_GREEN  = 2'b01,
               S_YELLOW = 2'b10;

    always @(negedge clk or posedge  rst_n) begin
        if (!rst_n) begin
            state <= S_RED;
            counter <= 1;
            led <= 2'b00;
        end else begin
            case (state)
                S_RED: begin
                    led <= 2'b00;
                    if (counter == 17) begin // 18s
                        state <= S_GREEN;
                        counter <= 0;
                    end else begin
                        counter <= counter + 1;
                    end
                end
                S_GREEN: begin
                    led <= 2'b01;
                    if (counter == 14) begin // 15s
                        state <= S_YELLOW;
                        counter <= 0;
                    end else begin
                        counter <= counter + 1;
                    end
                end
                S_YELLOW: begin
                    led <= 2'b10;
                    if (counter == 2) begin // 3s
                        state <= S_RED;
                        counter <= 0;
                    end else begin
                        counter <= counter + 1;
                    end
                end
                default: begin
                    state <= S_RED;
                    counter <= 0;
                    led <= 2'b00;
                end
            endcase
        end
    end
endmodule

traffic_fsm_signle_tb.v
`timescale 1ns/1ps
`include "traffic_fsm_single.v"

module traffic_fsm_single_tb;

    reg clk;
    reg rst_n;
    wire [1:0] led;

    // Instantiate the traffic_fsm_single module
    traffic_fsm_single uut (
        .clk(clk),
        .rst_n(rst_n),
        .led(led)
    );

    // Generate 1Hz clock (1s period => toggle every 0.5s)
    initial begin
        clk = 0;
        forever #500_000_000 clk = ~clk; // 0.5 second toggle
    end

    // Stimulus
    initial begin
        $dumpfile("traffic_fsm_single_tb.vcd");
        $dumpvars(0, traffic_fsm_single_tb);

        rst_n = 0;
        #1_000_000_000; // Wait 1 second
        rst_n = 1;

        #40_000_000_000; // Wait 40 seconds
        $finish;
    end
endmodule

traffic_fsm_single_tb.vcd
$date
	Fri Jun 13 08:42:31 2025
$end
$version
	Icarus Verilog
$end
$timescale
	1ps
$end
$scope module traffic_fsm_single_tb $end
$var wire 2 ! led [1:0] $end
$var reg 1 " clk $end
$var reg 1 # rst_n $end
$scope module uut $end
$var wire 1 " clk $end
$var wire 1 # rst_n $end
$var parameter 2 $ S_GREEN $end
$var parameter 2 % S_RED $end
$var parameter 2 & S_YELLOW $end
$var reg 5 ' counter [4:0] $end
$var reg 2 ( led [1:0] $end
$var reg 2 ) state [1:0] $end
$upscope $end
$upscope $end
$enddefinitions $end
$comment Show the parameter values. $end
$dumpall
b10 &
b0 %
b1 $
$end
#0
$dumpvars
b0 )
b0 (
b0 '
0#
0"
b0 !
$end
#500000000000
1"
#1000000000000
b1 '
0"
1#
#1500000000000
1"
#2000000000000
b10 '
0"
#2500000000000
1"
#3000000000000
b11 '
0"
#3500000000000
1"
#4000000000000
b100 '
0"
#4500000000000
1"
#5000000000000
b101 '
0"
#5500000000000
1"
#6000000000000
b110 '
0"
#6500000000000
1"
#7000000000000
b111 '
0"
#7500000000000
1"
#8000000000000
b1000 '
0"
#8500000000000
1"
#9000000000000
b1001 '
0"
#9500000000000
1"
#10000000000000
b1010 '
0"
#10500000000000
1"
#11000000000000
b1011 '
0"
#11500000000000
1"
#12000000000000
b1100 '
0"
#12500000000000
1"
#13000000000000
b1101 '
0"
#13500000000000
1"
#14000000000000
b1110 '
0"
#14500000000000
1"
#15000000000000
b1111 '
0"
#15500000000000
1"
#16000000000000
b10000 '
0"
#16500000000000
1"
#17000000000000
b10001 '
0"
#17500000000000
1"
#18000000000000
b0 '
b1 )
0"
#18500000000000
1"
#19000000000000
b1 '
b1 !
b1 (
0"
#19500000000000
1"
#20000000000000
b10 '
0"
#20500000000000
1"
#21000000000000
b11 '
0"
#21500000000000
1"
#22000000000000
b100 '
0"
#22500000000000
1"
#23000000000000
b101 '
0"
#23500000000000
1"
#24000000000000
b110 '
0"
#24500000000000
1"
#25000000000000
b111 '
0"
#25500000000000
1"
#26000000000000
b1000 '
0"
#26500000000000
1"
#27000000000000
b1001 '
0"
#27500000000000
1"
#28000000000000
b1010 '
0"
#28500000000000
1"
#29000000000000
b1011 '
0"
#29500000000000
1"
#30000000000000
b1100 '
0"
#30500000000000
1"
#31000000000000
b1101 '
0"
#31500000000000
1"
#32000000000000
b1110 '
0"
#32500000000000
1"
#33000000000000
b0 '
b10 )
0"
#33500000000000
1"
#34000000000000
b1 '
b10 !
b10 (
0"
#34500000000000
1"
#35000000000000
b10 '
0"
#35500000000000
1"
#36000000000000
b0 '
b0 )
0"
#36500000000000
1"
#37000000000000
b1 '
b0 !
b0 (
0"
#37500000000000
1"
#38000000000000
b10 '
0"
#38500000000000
1"
#39000000000000
b11 '
0"
#39500000000000
1"
#40000000000000
b100 '
0"
#40500000000000
1"
#41000000000000
b101 '
0"
